{
    "key": "group_578f8a1760fcb",
    "title": "Address",
    "fields": [
        {
            "key": "field_578f96bd304a8",
            "label": "Street Number",
            "name": "street_number",
            "type": "number",
            "instructions": "",
            "required": 0,
            "conditional_logic": 0,
            "wrapper": {
                "width": "",
                "class": "",
                "id": ""
            },
            "default_value": 133,
            "placeholder": "",
            "prepend": "",
            "append": "",
            "min": "",
            "max": "",
            "step": "",
            "readonly": 0,
            "disabled": 0
        },
        {
            "key": "field_578f8a2450883",
            "label": "Street Name",
            "name": "street_name",
            "type": "text",
            "instructions": "",
            "required": 0,
            "conditional_logic": 0,
            "wrapper": {
                "width": "",
                "class": "",
                "id": ""
            },
            "default_value": "",
            "placeholder": "",
            "prepend": "",
            "append": "",
            "maxlength": ""
        },
        {
            "key": "field_578f96e3d7aab",
            "label": "Street Abbreviation",
            "name": "street_abbrev",
            "type": "text",
            "instructions": "",
            "required": 0,
            "conditional_logic": 0,
            "wrapper": {
                "width": "",
                "class": "",
                "id": ""
            },
            "default_value": "",
            "placeholder": "St",
            "prepend": "",
            "append": "",
            "maxlength": "",
            "readonly": 0,
            "disabled": 0
        },
        {
            "key": "field_578f96f811743",
            "label": "Floor, Suite, or Unit Number",
            "name": "floor",
            "type": "text",
            "instructions": "",
            "required": 0,
            "conditional_logic": 0,
            "wrapper": {
                "width": "",
                "class": "",
                "id": ""
            },
            "default_value": "",
            "placeholder": "5th Floor",
            "prepend": "",
            "append": "",
            "maxlength": "",
            "readonly": 0,
            "disabled": 0
        },
        {
            "key": "field_578f8a4150884",
            "label": "City",
            "name": "city",
            "type": "text",
            "instructions": "",
            "required": 0,
            "conditional_logic": 0,
            "wrapper": {
                "width": "",
                "class": "",
                "id": ""
            },
            "default_value": "",
            "placeholder": "Boston",
            "prepend": "",
            "append": "",
            "maxlength": "",
            "readonly": 0,
            "disabled": 0
        },
        {
            "key": "field_578f8a5050885",
            "label": "State",
            "name": "state",
            "type": "select",
            "instructions": "",
            "required": 0,
            "conditional_logic": 0,
            "wrapper": {
                "width": "",
                "class": "",
                "id": ""
            },
            "choices": {
                "AL": "AL",
                "AK": "AK",
                "AZ": "AZ",
                "AR": "AR",
                "CA": "CA",
                "CO": "CO",
                "CT": "CT",
                "DC": "DC",
                "DE": "DE",
                "FL": "FL",
                "GA": "GA",
                "HI": "HI",
                "ID": "ID",
                "IL": "IL",
                "IN": "IN",
                "IA": "IA",
                "KS": "KS",
                "KY": "KY",
                "LA": "LA",
                "ME": "ME",
                "MD": "MD",
                "MA": "MA",
                "MI": "MI",
                "MN": "MN",
                "MS": "MS",
                "MO": "MO",
                "MT": "MT",
                "NE": "NE",
                "NV": "NV",
                "NH": "NH",
                "NJ": "NJ",
                "NM": "NM",
                "NY": "NY",
                "NC": "NC",
                "ND": "ND",
                "OH": "OH",
                "OK": "OK",
                "OR": "OR",
                "PA": "PA",
                "RI": "RI",
                "SC": "SC",
                "SD": "SD",
                "TN": "TN",
                "TX": "TX",
                "UT": "UT",
                "VT": "VT",
                "VA": "VA",
                "WA": "WA",
                "WV": "WV",
                "WI": "WI",
                "WY": "WY"
            },
            "default_value": [
                "MA"
            ],
            "allow_null": 0,
            "multiple": 0,
            "ui": 0,
            "ajax": 0,
            "return_format": "value",
            "placeholder": ""
        },
        {
            "key": "field_578f8b5992377",
            "label": "Zip Code",
            "name": "zip_code",
            "type": "text",
            "instructions": "",
            "required": 0,
            "conditional_logic": 0,
            "wrapper": {
                "width": "",
                "class": "",
                "id": ""
            },
            "default_value": "",
            "placeholder": "02114",
            "prepend": "",
            "append": "",
            "maxlength": "",
            "readonly": 0,
            "disabled": 0
        },
        {
            "key": "field_578f8c074f02a",
            "label": "Neighborhood",
            "name": "neighborhood",
            "type": "text",
            "instructions": "What do you call your neighborhood?",
            "required": 0,
            "conditional_logic": 0,
            "wrapper": {
                "width": "",
                "class": "",
                "id": ""
            },
            "default_value": "",
            "placeholder": "South End",
            "prepend": "",
            "append": "",
            "maxlength": "",
            "readonly": 0,
            "disabled": 0
        },
        {
            "key": "field_5790f1206af38",
            "label": "Map",
            "name": "map",
            "type": "google_map",
            "instructions": "",
            "required": 0,
            "conditional_logic": 0,
            "wrapper": {
                "width": "",
                "class": "",
                "id": ""
            },
            "center_lat": "42.3601",
            "center_lng": "-71.0589",
            "zoom": "",
            "height": ""
        }
    ],
    "location": [
        [
            {
                "param": "post_type",
                "operator": "==",
                "value": "agency"
            }
        ]
    ],
    "menu_order": 0,
    "position": "normal",
    "style": "default",
    "label_placement": "top",
    "instruction_placement": "label",
    "hide_on_screen": "",
    "active": 1,
    "description": "",
    "modified": 1478800645
}